LICENSE.md
MANIFEST.in
README.md
setup.py
django_theme_pixel.egg-info/PKG-INFO
django_theme_pixel.egg-info/SOURCES.txt
django_theme_pixel.egg-info/dependency_links.txt
django_theme_pixel.egg-info/not-zip-safe
django_theme_pixel.egg-info/top_level.txt
docs/blank.txt
theme_pixel/__init__.py
theme_pixel/admin.py
theme_pixel/apps.py
theme_pixel/forms.py
theme_pixel/models.py
theme_pixel/tests.py
theme_pixel/urls.py
theme_pixel/views.py
theme_pixel/migrations/__init__.py
theme_pixel/static/assets/img/checker_logo.png
theme_pixel/static/assets/img/megamenu_image.png
theme_pixel/static/assets/img/office.png
theme_pixel/static/assets/img/presentation-mockup-dashboard.png
theme_pixel/static/assets/img/presentation-mockup.png
theme_pixel/static/assets/img/sections-mockup.jpg
theme_pixel/static/assets/img/signature.svg
theme_pixel/static/assets/img/themesberg.svg
theme_pixel/static/assets/img/wavelogo.svg
theme_pixel/static/assets/img/blog/image-1.jpg
theme_pixel/static/assets/img/brand/dark.svg
theme_pixel/static/assets/img/brand/light.svg
theme_pixel/static/assets/img/brand/pixel-docs.svg
theme_pixel/static/assets/img/carousel/image-1.jpg
theme_pixel/static/assets/img/carousel/image-2.jpg
theme_pixel/static/assets/img/carousel/image-3.jpg
theme_pixel/static/assets/img/clients/airbnb.svg
theme_pixel/static/assets/img/clients/business-school.svg
theme_pixel/static/assets/img/clients/corsair.svg
theme_pixel/static/assets/img/clients/docker.svg
theme_pixel/static/assets/img/clients/ebay.svg
theme_pixel/static/assets/img/clients/elastic.svg
theme_pixel/static/assets/img/clients/forbes.svg
theme_pixel/static/assets/img/clients/google.svg
theme_pixel/static/assets/img/clients/northwestern.svg
theme_pixel/static/assets/img/clients/paypal.svg
theme_pixel/static/assets/img/clients/pinterest.svg
theme_pixel/static/assets/img/clients/university-of-chicago.svg
theme_pixel/static/assets/img/favicon/android-chrome-192x192.png
theme_pixel/static/assets/img/favicon/android-chrome-256x256.png
theme_pixel/static/assets/img/favicon/android-chrome-96x96.png
theme_pixel/static/assets/img/favicon/apple-touch-icon.png
theme_pixel/static/assets/img/favicon/browserconfig.xml
